equilipy/EquilibBatch.py
equilipy/EquilibSingle.py
equilipy/Errors.py
equilipy/FindTransition.py
equilipy/InputCondition.py
equilipy/InternalFunctions.py
equilipy/ListPhases.py
equilipy/Minimize.py
equilipy/NucleoScheil.py
equilipy/ParseCSDataBlock.py
equilipy/ParseCSDataBlockGibbs.py
equilipy/ParseCSDataBlockQKTO.py
equilipy/ParseCSDataBlockRKMP.py
equilipy/ParseCSDataBlockSUBG.py
equilipy/ParseCSDataBlockSUBL.py
equilipy/ParseCSHeader.py
equilipy/ParseHSCpFunctions.py
equilipy/PhaseSelection.py
equilipy/PostProcess.py
equilipy/ReadDAT.py
equilipy/ReadDict.py
equilipy/ScheilCooling.py
equilipy/Simplex.py
equilipy/SinglePhaseProperty.py
equilipy/SystemCheck.py
equilipy/__init__.py
equilipy/equilifort.cpython-311-i386-linux-musl.so
equilipy/utils.py
equilipy/variables.py
equilipy.libs/libgcc_s-e1925712.so.1
equilipy.libs/libgfortran-c0d93c94.so.5.0.0
equilipy.libs/libquadmath-bacbcf63.so.0.0.0
equilipy-0.2.1.dist-info/METADATA
equilipy-0.2.1.dist-info/WHEEL
equilipy-0.2.1.dist-info/entry_points.txt
equilipy-0.2.1.dist-info/top_level.txt
equilipy-0.2.1.dist-info/RECORD
equilipy-0.2.1.dist-info/licenses/LICENSE
