Metadata-Version: 2.4
Name: equilipy
Version: 0.2.1
Summary: A Gibbs energy minimization based on the CALPHAD approach
Author-email: Sunyong Kwon <kwons@ornl.gov>
License: BSD-3
Project-URL: documentation, https://ornl.github.io/Equilipy/
Project-URL: source, https://github.com/ORNL/Equilipy/
Requires-Python: >=3.9
License-File: LICENSE
Requires-Dist: numpy>=1.23
Requires-Dist: regex
Requires-Dist: dataclasses
Requires-Dist: meson
Requires-Dist: ninja
Requires-Dist: polars>=0.20.15
Requires-Dist: xlsx2csv
Requires-Dist: tqdm
Requires-Dist: fastexcel
Requires-Dist: typing
Requires-Dist: pydantic>=2.0
Dynamic: license-file
